case_search/__init__.py
case_search/case_data.csv
case_search/tax_rules.csv
case_search-0.5.0.dist-info/METADATA
case_search-0.5.0.dist-info/WHEEL
case_search-0.5.0.dist-info/entry_points.txt
case_search-0.5.0.dist-info/licenses/LICENSE
case_search-0.5.0.dist-info/RECORD
