Metadata-Version: 2.4
Name: case-search
Version: 0.5.0
Summary: A Model Context Protocol (MCP) server built with FastMCP for business tax information search (by BAN), web search via Serper API, and basic math calculations
Project-URL: Homepage, https://github.com/plion818/case-search
Project-URL: Repository, https://github.com/plion818/case-search
Author-email: plion818 <patrick89818pp@gmail.com>
License: MIT
License-File: LICENSE
Keywords: calculator,case-search,csv,fastmcp,math,mcp,model-context-protocol,query,serper,web-search
Classifier: Development Status :: 4 - Beta
Classifier: Intended Audience :: Developers
Classifier: License :: OSI Approved :: MIT License
Classifier: Programming Language :: Python :: 3
Classifier: Programming Language :: Python :: 3.10
Classifier: Programming Language :: Python :: 3.11
Classifier: Programming Language :: Python :: 3.12
Requires-Python: >=3.10
Requires-Dist: mcp[cli]>=1.24.0
Requires-Dist: pandas>=2.0.0
